filepattern-2.1.4.dist-info/RECORD
filepattern-2.1.4.dist-info/WHEEL
filepattern-2.1.4.dist-info/top_level.txt
filepattern-2.1.4.dist-info/METADATA
filepattern-2.1.4.dist-info/licenses/LICENSE
filepattern/functions.py
filepattern/libfilepattern.2.dylib
filepattern/backend.cpython-313-darwin.so
filepattern/libfilepattern.2.1.4.dylib
filepattern/_version.py
filepattern/libfilepattern.dylib
filepattern/filepattern.py
filepattern/__init__.py
filepattern/pydantic_filepattern.py
filepattern/.dylibs/libfilepattern.2.1.4.dylib
