Metadata-Version: 2.4
Name: filepattern
Version: 2.1.4
Summary: Utilities for parsing files in a directory based on a file name pattern.
Home-page: https://github.com/PolusAI/filepattern
Author: Jesse McKinzie, Nick Schaub
Author-email: Jesse.McKinzie@axleinfo.com, nick.schaub@nih.gov
Project-URL: Documentation, https://filepattern.readthedocs.io/en/latest/
Project-URL: Source, https://github.com/PolusAI/filepattern
Classifier: Programming Language :: Python :: 3
Classifier: License :: OSI Approved :: MIT License
Classifier: Operating System :: OS Independent
Requires-Python: >=3.6
License-File: LICENSE
Requires-Dist: pydantic
Dynamic: author
Dynamic: author-email
Dynamic: classifier
Dynamic: description
Dynamic: description-content-type
Dynamic: home-page
Dynamic: license-file
Dynamic: project-url
Dynamic: requires-dist
Dynamic: requires-python
Dynamic: summary
